library_example/__init__.py
library_example/main.py
library_example-0.4.0.dist-info/METADATA
library_example-0.4.0.dist-info/WHEEL
library_example-0.4.0.dist-info/entry_points.txt
library_example-0.4.0.dist-info/top_level.txt
library_example-0.4.0.dist-info/RECORD
