Metadata-Version: 2.1
Name: library_example
Version: 0.4.0
